MPComplex/mp_complex.py
MPComplex/mp_complex_tests.py
MPComplex/mp_complex_versus_mpc.py
MPComplex-1.1.dist-info/LICENSE
MPComplex-1.1.dist-info/METADATA
MPComplex-1.1.dist-info/WHEEL
MPComplex-1.1.dist-info/entry_points.txt
MPComplex-1.1.dist-info/top_level.txt
MPComplex-1.1.dist-info/RECORD
