Metadata-Version: 2.1
Name: MPComplex
Version: 1.1
Summary: This package contains implementation of the library "MPComplex". MPComplex is a data type supporting complex numbers which allow comparison and sorting operations.
Home-page: https://github.com/DigitalCreativeApkDev/MPComplex
Author: DigitalCreativeApkDev
Author-email: digitalcreativeapkdev2022@gmail.com
License: MIT
Platform: UNKNOWN
Classifier: Programming Language :: Python :: 3
Classifier: Programming Language :: Python :: 3.7
